lybic/__init__.py
lybic/authentication.py
lybic/base.py
lybic/dto.py
lybic/exceptions.py
lybic/lybic.py
lybic/mcp.py
lybic/project.py
lybic/pyautogui.py
lybic/sandbox.py
lybic/stats.py
lybic/tools.py
lybic/_api/__init__.py
lybic/_api/deprecation.py
lybic/_api/internal.py
lybic/action/__init__.py
lybic/action/android.py
lybic/action/common.py
lybic/action/computer.py
lybic/action/os.py
lybic/action/touch.py
lybic/gui_agents/__init__.py
lybic/gui_agents/api/__init__.py
lybic/gui_agents/api/agent.py
lybic/gui_agents/models/__init__.py
lybic/gui_agents/models/api_models.py
lybic-1.1.0.dist-info/licenses/LICENSE
lybic_sync/__init__.py
lybic_sync/base.py
lybic_sync/lybic_sync.py
lybic_sync/mcp.py
lybic_sync/project.py
lybic_sync/pyautogui.py
lybic_sync/sandbox.py
lybic_sync/stats.py
lybic_sync/tools.py
lybic-1.1.0.dist-info/METADATA
lybic-1.1.0.dist-info/WHEEL
lybic-1.1.0.dist-info/top_level.txt
lybic-1.1.0.dist-info/RECORD
