Metadata-Version: 2.4
Name: lybic
Version: 1.1.0
Summary: Lybic sdk for python
Home-page: https://github.com/lybic/lybic-sdk-python
Author: Lybic Development Team
Author-email: Lybic Development Team <team@lybic.ai>
License-Expression: MIT
Project-URL: Homepage, https://github.com/lybic/lybic-sdk-python
Project-URL: Issues, https://github.com/lybic/lybic-sdk-python/issues
Classifier: Programming Language :: Python :: 3
Classifier: Operating System :: OS Independent
Requires-Python: >=3.10
License-File: LICENSE
Requires-Dist: pydantic<3.0.0,>=2.10.6
Requires-Dist: pillow>=11.3.0
Requires-Dist: httpx>=0.28.1
Provides-Extra: mcp
Requires-Dist: mcp>=1.12.0; extra == "mcp"
Dynamic: author
Dynamic: home-page
Dynamic: license-file
Dynamic: requires-python
